{
    "@schema": "https://raw.githubusercontent.com/slicer/slicer/master/Modules/Loadable/Markups/Resources/Schema/markups-schema-v1.0.3.json#",
    "markups": [
        {
            "type": "Curve",
            "coordinateSystem": "LPS",
            "coordinateUnits": "mm",
            "locked": false,
            "fixedNumberOfControlPoints": false,
            "labelFormat": "%N-%d",
            "lastUsedControlPointNumber": 14,
            "controlPoints": [
                {
                    "id": "1",
                    "label": "Verse561_C6_LF_S-1",
                    "description": "",
                    "associatedNodeID": "",
                    "position": [
                        -17.929433822631836,
                        -131.3286895751953,
                        626.8846435546875
                    ],
                    "orientation": [
                        -1.0,
                        -0.0,
                        -0.0,
                        -0.0,
                        -1.0,
                        -0.0,
                        0.0,
                        0.0,
                        1.0
                    ],
                    "selected": true,
                    "locked": false,
                    "visibility": true,
                    "positionStatus": "defined"
                },
                {
                    "id": "2",
                    "label": "Verse561_C6_LF_S-2",
                    "description": "",
                    "associatedNodeID": "",
                    "position": [
                        -15.840588569641112,
                        -128.66192626953125,
                        629.7710571289062
                    ],
                    "orientation": [
                        -1.0,
                        -0.0,
                        -0.0,
                        -0.0,
                        -1.0,
                        -0.0,
                        0.0,
                        0.0,
                        1.0
                    ],
                    "selected": true,
                    "locked": false,
                    "visibility": true,
                    "positionStatus": "defined"
                },
                {
                    "id": "3",
                    "label": "Verse561_C6_LF_S-3",
                    "description": "",
                    "associatedNodeID": "",
                    "position": [
                        -13.52336883544922,
                        -126.36222839355467,
                        630.93603515625
                    ],
                    "orientation": [
                        -1.0,
                        -0.0,
                        -0.0,
                        -0.0,
                        -1.0,
                        -0.0,
                        0.0,
                        0.0,
                        1.0
                    ],
                    "selected": true,
                    "locked": false,
                    "visibility": true,
                    "positionStatus": "defined"
                },
                {
                    "id": "4",
                    "label": "Verse561_C6_LF_S-4",
                    "description": "",
                    "associatedNodeID": "",
                    "position": [
                        -10.774639129638672,
                        -124.23758697509766,
                        631.7839965820312
                    ],
                    "orientation": [
                        -1.0,
                        -0.0,
                        -0.0,
                        -0.0,
                        -1.0,
                        -0.0,
                        0.0,
                        0.0,
                        1.0
                    ],
                    "selected": true,
                    "locked": false,
                    "visibility": true,
                    "positionStatus": "defined"
                },
                {
                    "id": "5",
                    "label": "Verse561_C6_LF_S-5",
                    "description": "",
                    "associatedNodeID": "",
                    "position": [
                        -9.01220989227295,
                        -123.12064361572266,
                        632.27490234375
                    ],
                    "orientation": [
                        -1.0,
                        -0.0,
                        -0.0,
                        -0.0,
                        -1.0,
                        -0.0,
                        0.0,
                        0.0,
                        1.0
                    ],
                    "selected": true,
                    "locked": false,
                    "visibility": true,
                    "positionStatus": "defined"
                },
                {
                    "id": "6",
                    "label": "Verse561_C6_LF_S-6",
                    "description": "",
                    "associatedNodeID": "",
                    "position": [
                        -7.122885227203369,
                        -122.05355072021484,
                        632.6412353515625
                    ],
                    "orientation": [
                        -1.0,
                        -0.0,
                        -0.0,
                        -0.0,
                        -1.0,
                        -0.0,
                        0.0,
                        0.0,
                        1.0
                    ],
                    "selected": true,
                    "locked": false,
                    "visibility": true,
                    "positionStatus": "defined"
                },
                {
                    "id": "7",
                    "label": "Verse561_C6_LF_S-7",
                    "description": "",
                    "associatedNodeID": "",
                    "position": [
                        -5.318816184997559,
                        -121.6395263671875,
                        633.350341796875
                    ],
                    "orientation": [
                        -1.0,
                        -0.0,
                        -0.0,
                        -0.0,
                        -1.0,
                        -0.0,
                        0.0,
                        0.0,
                        1.0
                    ],
                    "selected": true,
                    "locked": false,
                    "visibility": true,
                    "positionStatus": "defined"
                },
                {
                    "id": "8",
                    "label": "Verse561_C6_LF_S-8",
                    "description": "",
                    "associatedNodeID": "",
                    "position": [
                        -2.981105327606201,
                        -121.69847869873048,
                        633.7814331054688
                    ],
                    "orientation": [
                        -1.0,
                        -0.0,
                        -0.0,
                        -0.0,
                        -1.0,
                        -0.0,
                        0.0,
                        0.0,
                        1.0
                    ],
                    "selected": true,
                    "locked": false,
                    "visibility": true,
                    "positionStatus": "defined"
                },
                {
                    "id": "9",
                    "label": "Verse561_C6_LF_S-9",
                    "description": "",
                    "associatedNodeID": "",
                    "position": [
                        -1.2054787874221802,
                        -122.33766174316406,
                        633.4710083007812
                    ],
                    "orientation": [
                        -1.0,
                        -0.0,
                        -0.0,
                        -0.0,
                        -1.0,
                        -0.0,
                        0.0,
                        0.0,
                        1.0
                    ],
                    "selected": true,
                    "locked": false,
                    "visibility": true,
                    "positionStatus": "defined"
                },
                {
                    "id": "10",
                    "label": "Verse561_C6_LF_S-10",
                    "description": "",
                    "associatedNodeID": "",
                    "position": [
                        0.711360514163971,
                        -123.19306182861328,
                        633.3447265625
                    ],
                    "orientation": [
                        -1.0,
                        -0.0,
                        -0.0,
                        -0.0,
                        -1.0,
                        -0.0,
                        0.0,
                        0.0,
                        1.0
                    ],
                    "selected": true,
                    "locked": false,
                    "visibility": true,
                    "positionStatus": "defined"
                },
                {
                    "id": "11",
                    "label": "Verse561_C6_LF_S-11",
                    "description": "",
                    "associatedNodeID": "",
                    "position": [
                        2.5749685764312744,
                        -124.3602066040039,
                        632.5824584960938
                    ],
                    "orientation": [
                        -1.0,
                        -0.0,
                        -0.0,
                        -0.0,
                        -1.0,
                        -0.0,
                        0.0,
                        0.0,
                        1.0
                    ],
                    "selected": true,
                    "locked": false,
                    "visibility": true,
                    "positionStatus": "defined"
                },
                {
                    "id": "12",
                    "label": "Verse561_C6_LF_S-12",
                    "description": "",
                    "associatedNodeID": "",
                    "position": [
                        5.307114601135254,
                        -126.2587890625,
                        631.3120727539062
                    ],
                    "orientation": [
                        -1.0,
                        -0.0,
                        -0.0,
                        -0.0,
                        -1.0,
                        -0.0,
                        0.0,
                        0.0,
                        1.0
                    ],
                    "selected": true,
                    "locked": false,
                    "visibility": true,
                    "positionStatus": "defined"
                },
                {
                    "id": "13",
                    "label": "Verse561_C6_LF_S-13",
                    "description": "",
                    "associatedNodeID": "",
                    "position": [
                        7.633866786956787,
                        -128.93099975585938,
                        630.3031005859375
                    ],
                    "orientation": [
                        -1.0,
                        -0.0,
                        -0.0,
                        -0.0,
                        -1.0,
                        -0.0,
                        0.0,
                        0.0,
                        1.0
                    ],
                    "selected": true,
                    "locked": false,
                    "visibility": true,
                    "positionStatus": "defined"
                },
                {
                    "id": "14",
                    "label": "Verse561_C6_LF_S-14",
                    "description": "",
                    "associatedNodeID": "",
                    "position": [
                        8.777274131774902,
                        -132.14573669433594,
                        628.2760620117188
                    ],
                    "orientation": [
                        -1.0,
                        -0.0,
                        -0.0,
                        -0.0,
                        -1.0,
                        -0.0,
                        0.0,
                        0.0,
                        1.0
                    ],
                    "selected": true,
                    "locked": false,
                    "visibility": true,
                    "positionStatus": "defined"
                }
            ],
            "measurements": [
                {
                    "name": "length",
                    "enabled": false,
                    "units": "mm",
                    "printFormat": "%-#4.4g%s"
                },
                {
                    "name": "curvature mean",
                    "enabled": false,
                    "printFormat": "%5.3f %s"
                },
                {
                    "name": "curvature max",
                    "enabled": false,
                    "printFormat": "%5.3f %s"
                },
                {
                    "name": "torsion mean",
                    "enabled": false,
                    "printFormat": "%5.3f %s"
                },
                {
                    "name": "torsion max",
                    "enabled": false,
                    "printFormat": "%5.3f %s"
                }
            ],
            "display": {
                "visibility": true,
                "opacity": 1.0,
                "color": [
                    0.0,
                    1.0,
                    0.0
                ],
                "selectedColor": [
                    0.0,
                    1.0,
                    0.0
                ],
                "activeColor": [
                    0.4,
                    1.0,
                    0.0
                ],
                "propertiesLabelVisibility": true,
                "pointLabelsVisibility": false,
                "textScale": 0.0,
                "glyphType": "Sphere3D",
                "glyphScale": 3.0,
                "glyphSize": 5.0,
                "useGlyphScale": true,
                "sliceProjection": false,
                "sliceProjectionUseFiducialColor": true,
                "sliceProjectionOutlinedBehindSlicePlane": false,
                "sliceProjectionColor": [
                    1.0,
                    1.0,
                    1.0
                ],
                "sliceProjectionOpacity": 0.6,
                "lineThickness": 0.2,
                "lineColorFadingStart": 1.0,
                "lineColorFadingEnd": 10.0,
                "lineColorFadingSaturation": 1.0,
                "lineColorFadingHueOffset": 0.0,
                "handlesInteractive": false,
                "translationHandleVisibility": true,
                "rotationHandleVisibility": true,
                "scaleHandleVisibility": true,
                "interactionHandleScale": 3.0,
                "snapMode": "toVisibleSurface"
            }
        }
    ]
}