{
    "@schema": "https://raw.githubusercontent.com/slicer/slicer/master/Modules/Loadable/Markups/Resources/Schema/markups-schema-v1.0.3.json#",
    "markups": [
        {
            "type": "ClosedCurve",
            "coordinateSystem": "LPS",
            "coordinateUnits": "mm",
            "locked": false,
            "fixedNumberOfControlPoints": false,
            "labelFormat": "%N-%d",
            "lastUsedControlPointNumber": 20,
            "controlPoints": [
                {
                    "id": "1",
                    "label": "Verse005_L1_CL_I_R-1",
                    "description": "",
                    "associatedNodeID": "",
                    "position": [
                        -8.345056533813477,
                        215.51979064941406,
                        -93.7899169921875
                    ],
                    "orientation": [
                        -1.0,
                        -0.0,
                        -0.0,
                        -0.0,
                        -1.0,
                        -0.0,
                        0.0,
                        0.0,
                        1.0
                    ],
                    "selected": true,
                    "locked": false,
                    "visibility": true,
                    "positionStatus": "defined"
                },
                {
                    "id": "2",
                    "label": "Verse005_L1_CL_I_R-2",
                    "description": "",
                    "associatedNodeID": "",
                    "position": [
                        -9.046966552734375,
                        217.49758911132812,
                        -93.55117797851562
                    ],
                    "orientation": [
                        -1.0,
                        -0.0,
                        -0.0,
                        -0.0,
                        -1.0,
                        -0.0,
                        0.0,
                        0.0,
                        1.0
                    ],
                    "selected": true,
                    "locked": false,
                    "visibility": true,
                    "positionStatus": "defined"
                },
                {
                    "id": "3",
                    "label": "Verse005_L1_CL_I_R-3",
                    "description": "",
                    "associatedNodeID": "",
                    "position": [
                        -9.392918586730957,
                        219.2705535888672,
                        -93.84745788574219
                    ],
                    "orientation": [
                        -1.0,
                        -0.0,
                        -0.0,
                        -0.0,
                        -1.0,
                        -0.0,
                        0.0,
                        0.0,
                        1.0
                    ],
                    "selected": true,
                    "locked": false,
                    "visibility": true,
                    "positionStatus": "defined"
                },
                {
                    "id": "4",
                    "label": "Verse005_L1_CL_I_R-4",
                    "description": "",
                    "associatedNodeID": "",
                    "position": [
                        -9.489886283874512,
                        220.9182891845703,
                        -94.74718475341797
                    ],
                    "orientation": [
                        -1.0,
                        -0.0,
                        -0.0,
                        -0.0,
                        -1.0,
                        -0.0,
                        0.0,
                        0.0,
                        1.0
                    ],
                    "selected": true,
                    "locked": false,
                    "visibility": true,
                    "positionStatus": "defined"
                },
                {
                    "id": "5",
                    "label": "Verse005_L1_CL_I_R-5",
                    "description": "",
                    "associatedNodeID": "",
                    "position": [
                        -9.242605209350586,
                        222.10525512695312,
                        -95.87008666992188
                    ],
                    "orientation": [
                        -1.0,
                        -0.0,
                        -0.0,
                        -0.0,
                        -1.0,
                        -0.0,
                        0.0,
                        0.0,
                        1.0
                    ],
                    "selected": true,
                    "locked": false,
                    "visibility": true,
                    "positionStatus": "defined"
                },
                {
                    "id": "6",
                    "label": "Verse005_L1_CL_I_R-6",
                    "description": "",
                    "associatedNodeID": "",
                    "position": [
                        -9.22214126586914,
                        222.7368621826172,
                        -97.6374740600586
                    ],
                    "orientation": [
                        -1.0,
                        -0.0,
                        -0.0,
                        -0.0,
                        -1.0,
                        -0.0,
                        0.0,
                        0.0,
                        1.0
                    ],
                    "selected": true,
                    "locked": false,
                    "visibility": true,
                    "positionStatus": "defined"
                },
                {
                    "id": "7",
                    "label": "Verse005_L1_CL_I_R-7",
                    "description": "",
                    "associatedNodeID": "",
                    "position": [
                        -9.231813430786133,
                        223.14060974121097,
                        -99.46012115478516
                    ],
                    "orientation": [
                        -1.0,
                        -0.0,
                        -0.0,
                        -0.0,
                        -1.0,
                        -0.0,
                        0.0,
                        0.0,
                        1.0
                    ],
                    "selected": true,
                    "locked": false,
                    "visibility": true,
                    "positionStatus": "defined"
                },
                {
                    "id": "8",
                    "label": "Verse005_L1_CL_I_R-8",
                    "description": "",
                    "associatedNodeID": "",
                    "position": [
                        -9.011343002319336,
                        223.03482055664065,
                        -101.25086212158205
                    ],
                    "orientation": [
                        -1.0,
                        -0.0,
                        -0.0,
                        -0.0,
                        -1.0,
                        -0.0,
                        0.0,
                        0.0,
                        1.0
                    ],
                    "selected": true,
                    "locked": false,
                    "visibility": true,
                    "positionStatus": "defined"
                },
                {
                    "id": "9",
                    "label": "Verse005_L1_CL_I_R-9",
                    "description": "",
                    "associatedNodeID": "",
                    "position": [
                        -8.625173568725586,
                        222.2264862060547,
                        -102.79595947265625
                    ],
                    "orientation": [
                        -1.0,
                        -0.0,
                        -0.0,
                        -0.0,
                        -1.0,
                        -0.0,
                        0.0,
                        0.0,
                        1.0
                    ],
                    "selected": true,
                    "locked": false,
                    "visibility": true,
                    "positionStatus": "defined"
                },
                {
                    "id": "10",
                    "label": "Verse005_L1_CL_I_R-10",
                    "description": "",
                    "associatedNodeID": "",
                    "position": [
                        -7.916730880737305,
                        220.83509826660156,
                        -103.98506164550781
                    ],
                    "orientation": [
                        -1.0,
                        -0.0,
                        -0.0,
                        -0.0,
                        -1.0,
                        -0.0,
                        0.0,
                        0.0,
                        1.0
                    ],
                    "selected": true,
                    "locked": false,
                    "visibility": true,
                    "positionStatus": "defined"
                },
                {
                    "id": "11",
                    "label": "Verse005_L1_CL_I_R-11",
                    "description": "",
                    "associatedNodeID": "",
                    "position": [
                        -7.471108913421631,
                        218.86343383789062,
                        -105.32239532470703
                    ],
                    "orientation": [
                        -1.0,
                        -0.0,
                        -0.0,
                        -0.0,
                        -1.0,
                        -0.0,
                        0.0,
                        0.0,
                        1.0
                    ],
                    "selected": true,
                    "locked": false,
                    "visibility": true,
                    "positionStatus": "defined"
                },
                {
                    "id": "12",
                    "label": "Verse005_L1_CL_I_R-12",
                    "description": "",
                    "associatedNodeID": "",
                    "position": [
                        -6.895029067993164,
                        216.60963439941406,
                        -106.30216217041016
                    ],
                    "orientation": [
                        -1.0,
                        -0.0,
                        -0.0,
                        -0.0,
                        -1.0,
                        -0.0,
                        0.0,
                        0.0,
                        1.0
                    ],
                    "selected": true,
                    "locked": false,
                    "visibility": true,
                    "positionStatus": "defined"
                },
                {
                    "id": "13",
                    "label": "Verse005_L1_CL_I_R-13",
                    "description": "",
                    "associatedNodeID": "",
                    "position": [
                        -6.081187725067139,
                        214.7260284423828,
                        -105.92811584472656
                    ],
                    "orientation": [
                        -1.0,
                        -0.0,
                        -0.0,
                        -0.0,
                        -1.0,
                        -0.0,
                        0.0,
                        0.0,
                        1.0
                    ],
                    "selected": true,
                    "locked": false,
                    "visibility": true,
                    "positionStatus": "defined"
                },
                {
                    "id": "14",
                    "label": "Verse005_L1_CL_I_R-14",
                    "description": "",
                    "associatedNodeID": "",
                    "position": [
                        -5.798938751220703,
                        213.22727966308594,
                        -104.77947235107422
                    ],
                    "orientation": [
                        -1.0,
                        -0.0,
                        -0.0,
                        -0.0,
                        -1.0,
                        -0.0,
                        0.0,
                        0.0,
                        1.0
                    ],
                    "selected": true,
                    "locked": false,
                    "visibility": true,
                    "positionStatus": "defined"
                },
                {
                    "id": "15",
                    "label": "Verse005_L1_CL_I_R-15",
                    "description": "",
                    "associatedNodeID": "",
                    "position": [
                        -5.612392902374268,
                        212.51914978027344,
                        -103.27630615234376
                    ],
                    "orientation": [
                        -1.0,
                        -0.0,
                        -0.0,
                        -0.0,
                        -1.0,
                        -0.0,
                        0.0,
                        0.0,
                        1.0
                    ],
                    "selected": true,
                    "locked": false,
                    "visibility": true,
                    "positionStatus": "defined"
                },
                {
                    "id": "16",
                    "label": "Verse005_L1_CL_I_R-16",
                    "description": "",
                    "associatedNodeID": "",
                    "position": [
                        -5.470921516418457,
                        212.1201171875,
                        -101.05535125732422
                    ],
                    "orientation": [
                        -1.0,
                        -0.0,
                        -0.0,
                        -0.0,
                        -1.0,
                        -0.0,
                        0.0,
                        0.0,
                        1.0
                    ],
                    "selected": true,
                    "locked": false,
                    "visibility": true,
                    "positionStatus": "defined"
                },
                {
                    "id": "17",
                    "label": "Verse005_L1_CL_I_R-17",
                    "description": "",
                    "associatedNodeID": "",
                    "position": [
                        -5.3346848487854,
                        212.0881805419922,
                        -98.83846282958984
                    ],
                    "orientation": [
                        -1.0,
                        -0.0,
                        -0.0,
                        -0.0,
                        -1.0,
                        -0.0,
                        0.0,
                        0.0,
                        1.0
                    ],
                    "selected": true,
                    "locked": false,
                    "visibility": true,
                    "positionStatus": "defined"
                },
                {
                    "id": "18",
                    "label": "Verse005_L1_CL_I_R-18",
                    "description": "",
                    "associatedNodeID": "",
                    "position": [
                        -5.5157294273376465,
                        212.4383544921875,
                        -96.8519287109375
                    ],
                    "orientation": [
                        -1.0,
                        -0.0,
                        -0.0,
                        -0.0,
                        -1.0,
                        -0.0,
                        0.0,
                        0.0,
                        1.0
                    ],
                    "selected": true,
                    "locked": false,
                    "visibility": true,
                    "positionStatus": "defined"
                },
                {
                    "id": "19",
                    "label": "Verse005_L1_CL_I_R-19",
                    "description": "",
                    "associatedNodeID": "",
                    "position": [
                        -6.384848117828369,
                        212.9683380126953,
                        -95.51991271972656
                    ],
                    "orientation": [
                        -1.0,
                        -0.0,
                        -0.0,
                        -0.0,
                        -1.0,
                        -0.0,
                        0.0,
                        0.0,
                        1.0
                    ],
                    "selected": true,
                    "locked": false,
                    "visibility": true,
                    "positionStatus": "defined"
                },
                {
                    "id": "20",
                    "label": "Verse005_L1_CL_I_R-20",
                    "description": "",
                    "associatedNodeID": "",
                    "position": [
                        -7.439947128295898,
                        213.98081970214844,
                        -94.37329864501953
                    ],
                    "orientation": [
                        -1.0,
                        -0.0,
                        -0.0,
                        -0.0,
                        -1.0,
                        -0.0,
                        0.0,
                        0.0,
                        1.0
                    ],
                    "selected": true,
                    "locked": false,
                    "visibility": true,
                    "positionStatus": "defined"
                }
            ],
            "measurements": [
                {
                    "name": "length",
                    "enabled": false,
                    "units": "mm",
                    "printFormat": "%-#4.4g%s"
                },
                {
                    "name": "curvature mean",
                    "enabled": false,
                    "printFormat": "%5.3f %s"
                },
                {
                    "name": "curvature max",
                    "enabled": false,
                    "printFormat": "%5.3f %s"
                },
                {
                    "name": "torsion mean",
                    "enabled": false,
                    "printFormat": "%5.3f %s"
                },
                {
                    "name": "torsion max",
                    "enabled": false,
                    "printFormat": "%5.3f %s"
                },
                {
                    "name": "area",
                    "enabled": false,
                    "units": "cm2",
                    "printFormat": "%-#4.4g%s"
                }
            ],
            "display": {
                "visibility": true,
                "opacity": 1.0,
                "color": [
                    0.0,
                    1.0,
                    0.0
                ],
                "selectedColor": [
                    0.0,
                    1.0,
                    0.0
                ],
                "activeColor": [
                    0.4,
                    1.0,
                    0.0
                ],
                "propertiesLabelVisibility": true,
                "pointLabelsVisibility": false,
                "textScale": 0.0,
                "glyphType": "Sphere3D",
                "glyphScale": 3.0,
                "glyphSize": 5.0,
                "useGlyphScale": true,
                "sliceProjection": false,
                "sliceProjectionUseFiducialColor": true,
                "sliceProjectionOutlinedBehindSlicePlane": false,
                "sliceProjectionColor": [
                    1.0,
                    1.0,
                    1.0
                ],
                "sliceProjectionOpacity": 0.6,
                "lineThickness": 0.2,
                "lineColorFadingStart": 1.0,
                "lineColorFadingEnd": 10.0,
                "lineColorFadingSaturation": 1.0,
                "lineColorFadingHueOffset": 0.0,
                "handlesInteractive": false,
                "translationHandleVisibility": true,
                "rotationHandleVisibility": true,
                "scaleHandleVisibility": true,
                "interactionHandleScale": 3.0,
                "snapMode": "toVisibleSurface"
            }
        }
    ]
}