{
    "@schema": "https://raw.githubusercontent.com/slicer/slicer/master/Modules/Loadable/Markups/Resources/Schema/markups-schema-v1.0.3.json#",
    "markups": [
        {
            "type": "ClosedCurve",
            "coordinateSystem": "LPS",
            "coordinateUnits": "mm",
            "locked": false,
            "fixedNumberOfControlPoints": false,
            "labelFormat": "%N-%d",
            "lastUsedControlPointNumber": 44,
            "controlPoints": [
                {
                    "id": "30",
                    "label": "Bc11702_C5_CL_I_R-30",
                    "description": "",
                    "associatedNodeID": "",
                    "position": [-23.166030883789063, 1.9694095849990845, -90.82754516601564],
                    "orientation": [-1.0, -0.0, -0.0, -0.0, -1.0, -0.0, 0.0, 0.0, 1.0],
                    "selected": true,
                    "locked": false,
                    "visibility": true,
                    "positionStatus": "defined"
                },
                {
                    "id": "31",
                    "label": "Bc11702_C5_CL_I_R-31",
                    "description": "",
                    "associatedNodeID": "",
                    "position": [-22.63212203979492, 3.876236915588379, -92.16934967041016],
                    "orientation": [-1.0, -0.0, -0.0, -0.0, -1.0, -0.0, 0.0, 0.0, 1.0],
                    "selected": true,
                    "locked": false,
                    "visibility": true,
                    "positionStatus": "defined"
                },
                {
                    "id": "32",
                    "label": "Bc11702_C5_CL_I_R-32",
                    "description": "",
                    "associatedNodeID": "",
                    "position": [-21.62227439880371, 5.300147533416748, -91.7248306274414],
                    "orientation": [-1.0, -0.0, -0.0, -0.0, -1.0, -0.0, 0.0, 0.0, 1.0],
                    "selected": true,
                    "locked": false,
                    "visibility": true,
                    "positionStatus": "defined"
                },
                {
                    "id": "33",
                    "label": "Bc11702_C5_CL_I_R-33",
                    "description": "",
                    "associatedNodeID": "",
                    "position": [-20.24416160583496, 6.931334972381592, -91.38690185546876],
                    "orientation": [-1.0, -0.0, -0.0, -0.0, -1.0, -0.0, 0.0, 0.0, 1.0],
                    "selected": true,
                    "locked": false,
                    "visibility": true,
                    "positionStatus": "defined"
                },
                {
                    "id": "34",
                    "label": "Bc11702_C5_CL_I_R-34",
                    "description": "",
                    "associatedNodeID": "",
                    "position": [-18.18395614624023, 8.348278045654297, -91.13773345947266],
                    "orientation": [-1.0, -0.0, -0.0, -0.0, -1.0, -0.0, 0.0, 0.0, 1.0],
                    "selected": true,
                    "locked": false,
                    "visibility": true,
                    "positionStatus": "defined"
                },
                {
                    "id": "35",
                    "label": "Bc11702_C5_CL_I_R-35",
                    "description": "",
                    "associatedNodeID": "",
                    "position": [-15.564473152160645, 9.220789909362791, -90.34375762939452],
                    "orientation": [-1.0, -0.0, -0.0, -0.0, -1.0, -0.0, 0.0, 0.0, 1.0],
                    "selected": true,
                    "locked": false,
                    "visibility": true,
                    "positionStatus": "defined"
                },
                {
                    "id": "36",
                    "label": "Bc11702_C5_CL_I_R-36",
                    "description": "",
                    "associatedNodeID": "",
                    "position": [-13.02312183380127, 9.004895210266113, -89.2940673828125],
                    "orientation": [-1.0, -0.0, -0.0, -0.0, -1.0, -0.0, 0.0, 0.0, 1.0],
                    "selected": true,
                    "locked": false,
                    "visibility": true,
                    "positionStatus": "defined"
                },
                {
                    "id": "37",
                    "label": "Bc11702_C5_CL_I_R-37",
                    "description": "",
                    "associatedNodeID": "",
                    "position": [-11.752613067626953, 6.727176189422607, -87.32518005371094],
                    "orientation": [-1.0, -0.0, -0.0, -0.0, -1.0, -0.0, 0.0, 0.0, 1.0],
                    "selected": true,
                    "locked": false,
                    "visibility": true,
                    "positionStatus": "defined"
                },
                {
                    "id": "38",
                    "label": "Bc11702_C5_CL_I_R-38",
                    "description": "",
                    "associatedNodeID": "",
                    "position": [-12.065282821655273, 3.9546456336975098, -86.45162963867188],
                    "orientation": [-1.0, -0.0, -0.0, -0.0, -1.0, -0.0, 0.0, 0.0, 1.0],
                    "selected": true,
                    "locked": false,
                    "visibility": true,
                    "positionStatus": "defined"
                },
                {
                    "id": "39",
                    "label": "Bc11702_C5_CL_I_R-39",
                    "description": "",
                    "associatedNodeID": "",
                    "position": [-13.353214263916016, 1.5535547733306885, -86.55101013183594],
                    "orientation": [-1.0, -0.0, -0.0, -0.0, -1.0, -0.0, 0.0, 0.0, 1.0],
                    "selected": true,
                    "locked": false,
                    "visibility": true,
                    "positionStatus": "defined"
                },
                {
                    "id": "40",
                    "label": "Bc11702_C5_CL_I_R-40",
                    "description": "",
                    "associatedNodeID": "",
                    "position": [-16.002723693847656, -0.1612454205751419, -86.78559875488281],
                    "orientation": [-1.0, -0.0, -0.0, -0.0, -1.0, -0.0, 0.0, 0.0, 1.0],
                    "selected": true,
                    "locked": false,
                    "visibility": true,
                    "positionStatus": "defined"
                },
                {
                    "id": "41",
                    "label": "Bc11702_C5_CL_I_R-41",
                    "description": "",
                    "associatedNodeID": "",
                    "position": [-18.615970611572266, -0.9867175817489624, -87.25302124023438],
                    "orientation": [-1.0, -0.0, -0.0, -0.0, -1.0, -0.0, 0.0, 0.0, 1.0],
                    "selected": true,
                    "locked": false,
                    "visibility": true,
                    "positionStatus": "defined"
                },
                {
                    "id": "42",
                    "label": "Bc11702_C5_CL_I_R-42",
                    "description": "",
                    "associatedNodeID": "",
                    "position": [-20.39717674255371, -0.7927431464195251, -87.96935272216797],
                    "orientation": [-1.0, -0.0, -0.0, -0.0, -1.0, -0.0, 0.0, 0.0, 1.0],
                    "selected": true,
                    "locked": false,
                    "visibility": true,
                    "positionStatus": "defined"
                },
                {
                    "id": "43",
                    "label": "Bc11702_C5_CL_I_R-43",
                    "description": "",
                    "associatedNodeID": "",
                    "position": [-21.73204803466797, -0.31740692257881165, -88.2820816040039],
                    "orientation": [-1.0, -0.0, -0.0, -0.0, -1.0, -0.0, 0.0, 0.0, 1.0],
                    "selected": true,
                    "locked": false,
                    "visibility": true,
                    "positionStatus": "defined"
                },
                {
                    "id": "44",
                    "label": "Bc11702_C5_CL_I_R-44",
                    "description": "",
                    "associatedNodeID": "",
                    "position": [-22.863161087036133, 0.6221890449523926, -89.8105697631836],
                    "orientation": [-1.0, -0.0, -0.0, -0.0, -1.0, -0.0, 0.0, 0.0, 1.0],
                    "selected": true,
                    "locked": false,
                    "visibility": true,
                    "positionStatus": "defined"
                }
            ],
            "measurements": [
                {
                    "name": "length",
                    "enabled": false,
                    "units": "mm",
                    "printFormat": "%-#4.4g%s"
                },
                {
                    "name": "curvature mean",
                    "enabled": false,
                    "printFormat": "%5.3f %s"
                },
                {
                    "name": "curvature max",
                    "enabled": false,
                    "printFormat": "%5.3f %s"
                },
                {
                    "name": "torsion mean",
                    "enabled": false,
                    "printFormat": "%5.3f %s"
                },
                {
                    "name": "torsion max",
                    "enabled": false,
                    "printFormat": "%5.3f %s"
                },
                {
                    "name": "area",
                    "enabled": false,
                    "units": "cm2",
                    "printFormat": "%-#4.4g%s"
                }
            ],
            "display": {
                "visibility": true,
                "opacity": 1.0,
                "color": [0.0, 1.0, 0.0],
                "selectedColor": [0.0, 1.0, 0.0],
                "activeColor": [0.4, 1.0, 0.0],
                "propertiesLabelVisibility": true,
                "pointLabelsVisibility": false,
                "textScale": 0.0,
                "glyphType": "Sphere3D",
                "glyphScale": 3.0,
                "glyphSize": 5.0,
                "useGlyphScale": true,
                "sliceProjection": false,
                "sliceProjectionUseFiducialColor": true,
                "sliceProjectionOutlinedBehindSlicePlane": false,
                "sliceProjectionColor": [1.0, 1.0, 1.0],
                "sliceProjectionOpacity": 0.6,
                "lineThickness": 0.2,
                "lineColorFadingStart": 1.0,
                "lineColorFadingEnd": 10.0,
                "lineColorFadingSaturation": 1.0,
                "lineColorFadingHueOffset": 0.0,
                "handlesInteractive": false,
                "translationHandleVisibility": true,
                "rotationHandleVisibility": true,
                "scaleHandleVisibility": true,
                "interactionHandleScale": 3.0,
                "snapMode": "toVisibleSurface"
            }
        }
    ]
}