{
    "@schema": "https://raw.githubusercontent.com/slicer/slicer/master/Modules/Loadable/Markups/Resources/Schema/markups-schema-v1.0.3.json#",
    "markups": [
        {
            "type": "Curve",
            "coordinateSystem": "LPS",
            "coordinateUnits": "mm",
            "locked": false,
            "fixedNumberOfControlPoints": false,
            "labelFormat": "%N-%d",
            "lastUsedControlPointNumber": 7,
            "controlPoints": [
                {
                    "id": "1",
                    "label": "Verse561_T12_LF_I_1-1",
                    "description": "",
                    "associatedNodeID": "",
                    "position": [
                        -10.00466537475586,
                        -67.87960815429688,
                        327.5772705078125
                    ],
                    "orientation": [
                        -1.0,
                        -0.0,
                        -0.0,
                        -0.0,
                        -1.0,
                        -0.0,
                        0.0,
                        0.0,
                        1.0
                    ],
                    "selected": true,
                    "locked": false,
                    "visibility": true,
                    "positionStatus": "defined"
                },
                {
                    "id": "2",
                    "label": "Verse561_T12_LF_I_1-2",
                    "description": "",
                    "associatedNodeID": "",
                    "position": [
                        -7.11993408203125,
                        -63.738460540771484,
                        323.35980224609375
                    ],
                    "orientation": [
                        -1.0,
                        -0.0,
                        -0.0,
                        -0.0,
                        -1.0,
                        -0.0,
                        0.0,
                        0.0,
                        1.0
                    ],
                    "selected": true,
                    "locked": false,
                    "visibility": true,
                    "positionStatus": "defined"
                },
                {
                    "id": "3",
                    "label": "Verse561_T12_LF_I_1-3",
                    "description": "",
                    "associatedNodeID": "",
                    "position": [
                        -4.409073829650879,
                        -60.66586685180664,
                        318.44921875
                    ],
                    "orientation": [
                        -1.0,
                        -0.0,
                        -0.0,
                        -0.0,
                        -1.0,
                        -0.0,
                        0.0,
                        0.0,
                        1.0
                    ],
                    "selected": true,
                    "locked": false,
                    "visibility": true,
                    "positionStatus": "defined"
                },
                {
                    "id": "4",
                    "label": "Verse561_T12_LF_I_1-4",
                    "description": "",
                    "associatedNodeID": "",
                    "position": [
                        -0.7336174845695496,
                        -56.30436325073242,
                        313.0999755859375
                    ],
                    "orientation": [
                        -1.0,
                        -0.0,
                        -0.0,
                        -0.0,
                        -1.0,
                        -0.0,
                        0.0,
                        0.0,
                        1.0
                    ],
                    "selected": true,
                    "locked": false,
                    "visibility": true,
                    "positionStatus": "defined"
                },
                {
                    "id": "5",
                    "label": "Verse561_T12_LF_I_1-5",
                    "description": "",
                    "associatedNodeID": "",
                    "position": [
                        3.56235671043396,
                        -59.97026824951172,
                        317.8686828613281
                    ],
                    "orientation": [
                        -1.0,
                        -0.0,
                        -0.0,
                        -0.0,
                        -1.0,
                        -0.0,
                        0.0,
                        0.0,
                        1.0
                    ],
                    "selected": true,
                    "locked": false,
                    "visibility": true,
                    "positionStatus": "defined"
                },
                {
                    "id": "6",
                    "label": "Verse561_T12_LF_I_1-6",
                    "description": "",
                    "associatedNodeID": "",
                    "position": [
                        8.81613826751709,
                        -62.97053527832031,
                        323.2140808105469
                    ],
                    "orientation": [
                        -1.0,
                        -0.0,
                        -0.0,
                        -0.0,
                        -1.0,
                        -0.0,
                        0.0,
                        0.0,
                        1.0
                    ],
                    "selected": true,
                    "locked": false,
                    "visibility": true,
                    "positionStatus": "defined"
                },
                {
                    "id": "7",
                    "label": "Verse561_T12_LF_I_1-7",
                    "description": "",
                    "associatedNodeID": "",
                    "position": [
                        12.046013832092285,
                        -66.52383422851562,
                        325.9051513671875
                    ],
                    "orientation": [
                        -1.0,
                        -0.0,
                        -0.0,
                        -0.0,
                        -1.0,
                        -0.0,
                        0.0,
                        0.0,
                        1.0
                    ],
                    "selected": true,
                    "locked": false,
                    "visibility": true,
                    "positionStatus": "defined"
                }
            ],
            "measurements": [
                {
                    "name": "length",
                    "enabled": false,
                    "units": "mm",
                    "printFormat": "%-#4.4g%s"
                },
                {
                    "name": "curvature mean",
                    "enabled": false,
                    "printFormat": "%5.3f %s"
                },
                {
                    "name": "curvature max",
                    "enabled": false,
                    "printFormat": "%5.3f %s"
                },
                {
                    "name": "torsion mean",
                    "enabled": false,
                    "printFormat": "%5.3f %s"
                },
                {
                    "name": "torsion max",
                    "enabled": false,
                    "printFormat": "%5.3f %s"
                }
            ],
            "display": {
                "visibility": true,
                "opacity": 1.0,
                "color": [
                    0.0,
                    1.0,
                    0.0
                ],
                "selectedColor": [
                    0.0,
                    1.0,
                    0.0
                ],
                "activeColor": [
                    0.4,
                    1.0,
                    0.0
                ],
                "propertiesLabelVisibility": true,
                "pointLabelsVisibility": false,
                "textScale": 0.0,
                "glyphType": "Sphere3D",
                "glyphScale": 3.0,
                "glyphSize": 5.0,
                "useGlyphScale": true,
                "sliceProjection": false,
                "sliceProjectionUseFiducialColor": true,
                "sliceProjectionOutlinedBehindSlicePlane": false,
                "sliceProjectionColor": [
                    1.0,
                    1.0,
                    1.0
                ],
                "sliceProjectionOpacity": 0.6,
                "lineThickness": 0.2,
                "lineColorFadingStart": 1.0,
                "lineColorFadingEnd": 10.0,
                "lineColorFadingSaturation": 1.0,
                "lineColorFadingHueOffset": 0.0,
                "handlesInteractive": false,
                "translationHandleVisibility": true,
                "rotationHandleVisibility": true,
                "scaleHandleVisibility": true,
                "interactionHandleScale": 3.0,
                "snapMode": "toVisibleSurface"
            }
        }
    ]
}