{
    "@schema": "https://raw.githubusercontent.com/slicer/slicer/master/Modules/Loadable/Markups/Resources/Schema/markups-schema-v1.0.3.json#",
    "markups": [
        {
            "type": "Curve",
            "coordinateSystem": "LPS",
            "coordinateUnits": "mm",
            "locked": false,
            "fixedNumberOfControlPoints": false,
            "labelFormat": "%N-%d",
            "lastUsedControlPointNumber": 10,
            "controlPoints": [
                {
                    "id": "1",
                    "label": "Verse581_T9_ALL_S-1",
                    "description": "",
                    "associatedNodeID": "",
                    "position": [
                        24.56970596313477,
                        176.75363159179688,
                        -486.0715026855469
                    ],
                    "orientation": [
                        -1.0,
                        -0.0,
                        -0.0,
                        -0.0,
                        -1.0,
                        -0.0,
                        0.0,
                        0.0,
                        1.0
                    ],
                    "selected": true,
                    "locked": false,
                    "visibility": true,
                    "positionStatus": "defined"
                },
                {
                    "id": "2",
                    "label": "Verse581_T9_ALL_S-2",
                    "description": "",
                    "associatedNodeID": "",
                    "position": [
                        22.134456634521484,
                        172.7744140625,
                        -485.7395629882813
                    ],
                    "orientation": [
                        -1.0,
                        -0.0,
                        -0.0,
                        -0.0,
                        -1.0,
                        -0.0,
                        0.0,
                        0.0,
                        1.0
                    ],
                    "selected": true,
                    "locked": false,
                    "visibility": true,
                    "positionStatus": "defined"
                },
                {
                    "id": "3",
                    "label": "Verse581_T9_ALL_S-3",
                    "description": "",
                    "associatedNodeID": "",
                    "position": [
                        18.30510902404785,
                        169.38308715820312,
                        -485.75335693359375
                    ],
                    "orientation": [
                        -1.0,
                        -0.0,
                        -0.0,
                        -0.0,
                        -1.0,
                        -0.0,
                        0.0,
                        0.0,
                        1.0
                    ],
                    "selected": true,
                    "locked": false,
                    "visibility": true,
                    "positionStatus": "defined"
                },
                {
                    "id": "4",
                    "label": "Verse581_T9_ALL_S-4",
                    "description": "",
                    "associatedNodeID": "",
                    "position": [
                        13.890376091003418,
                        167.50839233398438,
                        -485.8897399902344
                    ],
                    "orientation": [
                        -1.0,
                        -0.0,
                        -0.0,
                        -0.0,
                        -1.0,
                        -0.0,
                        0.0,
                        0.0,
                        1.0
                    ],
                    "selected": true,
                    "locked": false,
                    "visibility": true,
                    "positionStatus": "defined"
                },
                {
                    "id": "5",
                    "label": "Verse581_T9_ALL_S-5",
                    "description": "",
                    "associatedNodeID": "",
                    "position": [
                        8.367859840393066,
                        167.2811737060547,
                        -486.5335998535156
                    ],
                    "orientation": [
                        -1.0,
                        -0.0,
                        -0.0,
                        -0.0,
                        -1.0,
                        -0.0,
                        0.0,
                        0.0,
                        1.0
                    ],
                    "selected": true,
                    "locked": false,
                    "visibility": true,
                    "positionStatus": "defined"
                },
                {
                    "id": "6",
                    "label": "Verse581_T9_ALL_S-6",
                    "description": "",
                    "associatedNodeID": "",
                    "position": [
                        3.8441836833953857,
                        168.81564331054688,
                        -486.6598510742187
                    ],
                    "orientation": [
                        -1.0,
                        -0.0,
                        -0.0,
                        -0.0,
                        -1.0,
                        -0.0,
                        0.0,
                        0.0,
                        1.0
                    ],
                    "selected": true,
                    "locked": false,
                    "visibility": true,
                    "positionStatus": "defined"
                },
                {
                    "id": "7",
                    "label": "Verse581_T9_ALL_S-7",
                    "description": "",
                    "associatedNodeID": "",
                    "position": [
                        0.6306353211402893,
                        171.008056640625,
                        -486.7650146484375
                    ],
                    "orientation": [
                        -1.0,
                        -0.0,
                        -0.0,
                        -0.0,
                        -1.0,
                        -0.0,
                        0.0,
                        0.0,
                        1.0
                    ],
                    "selected": true,
                    "locked": false,
                    "visibility": true,
                    "positionStatus": "defined"
                },
                {
                    "id": "8",
                    "label": "Verse581_T9_ALL_S-8",
                    "description": "",
                    "associatedNodeID": "",
                    "position": [
                        -1.120896339416504,
                        173.58999633789065,
                        -486.9281311035156
                    ],
                    "orientation": [
                        -1.0,
                        -0.0,
                        -0.0,
                        -0.0,
                        -1.0,
                        -0.0,
                        0.0,
                        0.0,
                        1.0
                    ],
                    "selected": true,
                    "locked": false,
                    "visibility": true,
                    "positionStatus": "defined"
                },
                {
                    "id": "9",
                    "label": "Verse581_T9_ALL_S-9",
                    "description": "",
                    "associatedNodeID": "",
                    "position": [
                        -2.502674102783203,
                        175.75021362304688,
                        -487.07867431640625
                    ],
                    "orientation": [
                        -1.0,
                        -0.0,
                        -0.0,
                        -0.0,
                        -1.0,
                        -0.0,
                        0.0,
                        0.0,
                        1.0
                    ],
                    "selected": true,
                    "locked": false,
                    "visibility": true,
                    "positionStatus": "defined"
                },
                {
                    "id": "10",
                    "label": "Verse581_T9_ALL_S-10",
                    "description": "",
                    "associatedNodeID": "",
                    "position": [
                        -3.3849475383758545,
                        178.1004180908203,
                        -487.2380676269531
                    ],
                    "orientation": [
                        -1.0,
                        -0.0,
                        -0.0,
                        -0.0,
                        -1.0,
                        -0.0,
                        0.0,
                        0.0,
                        1.0
                    ],
                    "selected": true,
                    "locked": false,
                    "visibility": true,
                    "positionStatus": "defined"
                }
            ],
            "measurements": [
                {
                    "name": "length",
                    "enabled": false,
                    "units": "mm",
                    "printFormat": "%-#4.4g%s"
                },
                {
                    "name": "curvature mean",
                    "enabled": false,
                    "printFormat": "%5.3f %s"
                },
                {
                    "name": "curvature max",
                    "enabled": false,
                    "printFormat": "%5.3f %s"
                },
                {
                    "name": "torsion mean",
                    "enabled": false,
                    "printFormat": "%5.3f %s"
                },
                {
                    "name": "torsion max",
                    "enabled": false,
                    "printFormat": "%5.3f %s"
                }
            ],
            "display": {
                "visibility": true,
                "opacity": 1.0,
                "color": [
                    0.0,
                    1.0,
                    0.0
                ],
                "selectedColor": [
                    0.0,
                    1.0,
                    0.0
                ],
                "activeColor": [
                    0.4,
                    1.0,
                    0.0
                ],
                "propertiesLabelVisibility": true,
                "pointLabelsVisibility": false,
                "textScale": 0.0,
                "glyphType": "Sphere3D",
                "glyphScale": 3.0,
                "glyphSize": 5.0,
                "useGlyphScale": true,
                "sliceProjection": false,
                "sliceProjectionUseFiducialColor": true,
                "sliceProjectionOutlinedBehindSlicePlane": false,
                "sliceProjectionColor": [
                    1.0,
                    1.0,
                    1.0
                ],
                "sliceProjectionOpacity": 0.6,
                "lineThickness": 0.2,
                "lineColorFadingStart": 1.0,
                "lineColorFadingEnd": 10.0,
                "lineColorFadingSaturation": 1.0,
                "lineColorFadingHueOffset": 0.0,
                "handlesInteractive": false,
                "translationHandleVisibility": true,
                "rotationHandleVisibility": true,
                "scaleHandleVisibility": true,
                "interactionHandleScale": 3.0,
                "snapMode": "toVisibleSurface"
            }
        }
    ]
}