{
    "@schema": "https://raw.githubusercontent.com/slicer/slicer/master/Modules/Loadable/Markups/Resources/Schema/markups-schema-v1.0.3.json#",
    "markups": [
        {
            "type": "Curve",
            "coordinateSystem": "LPS",
            "coordinateUnits": "mm",
            "locked": false,
            "fixedNumberOfControlPoints": false,
            "labelFormat": "%N-%d",
            "lastUsedControlPointNumber": 15,
            "controlPoints": [
                {
                    "id": "1",
                    "label": "Verse561_T3_ALL_S-1Verse561_T3_ALL_S-2",
                    "description": "",
                    "associatedNodeID": "",
                    "position": [
                        12.438862800598145,
                        -107.622802734375,
                        555.900634765625
                    ],
                    "orientation": [
                        -1.0,
                        -0.0,
                        -0.0,
                        -0.0,
                        -1.0,
                        -0.0,
                        0.0,
                        0.0,
                        1.0
                    ],
                    "selected": true,
                    "locked": false,
                    "visibility": true,
                    "positionStatus": "defined"
                },
                {
                    "id": "2",
                    "label": "Verse561_T3_ALL_S-3",
                    "description": "",
                    "associatedNodeID": "",
                    "position": [
                        11.792969703674316,
                        -109.806396484375,
                        555.6021728515625
                    ],
                    "orientation": [
                        -1.0,
                        -0.0,
                        -0.0,
                        -0.0,
                        -1.0,
                        -0.0,
                        0.0,
                        0.0,
                        1.0
                    ],
                    "selected": true,
                    "locked": false,
                    "visibility": true,
                    "positionStatus": "defined"
                },
                {
                    "id": "3",
                    "label": "Verse561_T3_ALL_S-4Verse561_T3_ALL_S-5",
                    "description": "",
                    "associatedNodeID": "",
                    "position": [
                        10.558854103088379,
                        -111.37318420410156,
                        555.0589599609375
                    ],
                    "orientation": [
                        -1.0,
                        -0.0,
                        -0.0,
                        -0.0,
                        -1.0,
                        -0.0,
                        0.0,
                        0.0,
                        1.0
                    ],
                    "selected": true,
                    "locked": false,
                    "visibility": true,
                    "positionStatus": "defined"
                },
                {
                    "id": "4",
                    "label": "Verse561_T3_ALL_S-6Verse561_T3_ALL_S-7",
                    "description": "",
                    "associatedNodeID": "",
                    "position": [
                        9.186360359191895,
                        -113.24602508544922,
                        554.9036865234375
                    ],
                    "orientation": [
                        -1.0,
                        -0.0,
                        -0.0,
                        -0.0,
                        -1.0,
                        -0.0,
                        0.0,
                        0.0,
                        1.0
                    ],
                    "selected": true,
                    "locked": false,
                    "visibility": true,
                    "positionStatus": "defined"
                },
                {
                    "id": "5",
                    "label": "Verse561_T3_ALL_S-8",
                    "description": "",
                    "associatedNodeID": "",
                    "position": [
                        7.491835594177246,
                        -114.22543334960938,
                        554.6513061523438
                    ],
                    "orientation": [
                        -1.0,
                        -0.0,
                        -0.0,
                        -0.0,
                        -1.0,
                        -0.0,
                        0.0,
                        0.0,
                        1.0
                    ],
                    "selected": true,
                    "locked": false,
                    "visibility": true,
                    "positionStatus": "defined"
                },
                {
                    "id": "6",
                    "label": "Verse561_T3_ALL_S-9Verse561_T3_ALL_S-10",
                    "description": "",
                    "associatedNodeID": "",
                    "position": [
                        5.647462368011475,
                        -114.9411392211914,
                        554.3987426757812
                    ],
                    "orientation": [
                        -1.0,
                        -0.0,
                        -0.0,
                        -0.0,
                        -1.0,
                        -0.0,
                        0.0,
                        0.0,
                        1.0
                    ],
                    "selected": true,
                    "locked": false,
                    "visibility": true,
                    "positionStatus": "defined"
                },
                {
                    "id": "7",
                    "label": "Verse561_T3_ALL_S-11",
                    "description": "",
                    "associatedNodeID": "",
                    "position": [
                        3.9347798824310303,
                        -115.33222198486328,
                        554.2975463867188
                    ],
                    "orientation": [
                        -1.0,
                        -0.0,
                        -0.0,
                        -0.0,
                        -1.0,
                        -0.0,
                        0.0,
                        0.0,
                        1.0
                    ],
                    "selected": true,
                    "locked": false,
                    "visibility": true,
                    "positionStatus": "defined"
                },
                {
                    "id": "8",
                    "label": "Verse561_T3_ALL_S-12Verse561_T3_ALL_S-13",
                    "description": "",
                    "associatedNodeID": "",
                    "position": [
                        2.294215440750122,
                        -115.54680633544922,
                        554.1458129882812
                    ],
                    "orientation": [
                        -1.0,
                        -0.0,
                        -0.0,
                        -0.0,
                        -1.0,
                        -0.0,
                        0.0,
                        0.0,
                        1.0
                    ],
                    "selected": true,
                    "locked": false,
                    "visibility": true,
                    "positionStatus": "defined"
                },
                {
                    "id": "9",
                    "label": "Verse561_T3_ALL_S-14Verse561_T3_ALL_S-15",
                    "description": "",
                    "associatedNodeID": "",
                    "position": [
                        0.7238528728485107,
                        -115.60118103027344,
                        554.1250610351562
                    ],
                    "orientation": [
                        -1.0,
                        -0.0,
                        -0.0,
                        -0.0,
                        -1.0,
                        -0.0,
                        0.0,
                        0.0,
                        1.0
                    ],
                    "selected": true,
                    "locked": false,
                    "visibility": true,
                    "positionStatus": "defined"
                },
                {
                    "id": "10",
                    "label": "Verse561_T3_ALL_S-16Verse561_T3_ALL_S-17",
                    "description": "",
                    "associatedNodeID": "",
                    "position": [
                        -1.3412504196166992,
                        -115.46878814697266,
                        553.9833374023438
                    ],
                    "orientation": [
                        -1.0,
                        -0.0,
                        -0.0,
                        -0.0,
                        -1.0,
                        -0.0,
                        0.0,
                        0.0,
                        1.0
                    ],
                    "selected": true,
                    "locked": false,
                    "visibility": true,
                    "positionStatus": "defined"
                },
                {
                    "id": "11",
                    "label": "Verse561_T3_ALL_S-18Verse561_T3_ALL_S-19",
                    "description": "",
                    "associatedNodeID": "",
                    "position": [
                        -3.435645341873169,
                        -115.01687622070312,
                        553.785888671875
                    ],
                    "orientation": [
                        -1.0,
                        -0.0,
                        -0.0,
                        -0.0,
                        -1.0,
                        -0.0,
                        0.0,
                        0.0,
                        1.0
                    ],
                    "selected": true,
                    "locked": false,
                    "visibility": true,
                    "positionStatus": "defined"
                },
                {
                    "id": "12",
                    "label": "Verse561_T3_ALL_S-20",
                    "description": "",
                    "associatedNodeID": "",
                    "position": [
                        -5.387213230133057,
                        -114.09040069580078,
                        553.79931640625
                    ],
                    "orientation": [
                        -1.0,
                        -0.0,
                        -0.0,
                        -0.0,
                        -1.0,
                        -0.0,
                        0.0,
                        0.0,
                        1.0
                    ],
                    "selected": true,
                    "locked": false,
                    "visibility": true,
                    "positionStatus": "defined"
                },
                {
                    "id": "13",
                    "label": "Verse561_T3_ALL_S-21Verse561_T3_ALL_S-23",
                    "description": "",
                    "associatedNodeID": "",
                    "position": [
                        -7.182400226593018,
                        -112.79593658447266,
                        553.97216796875
                    ],
                    "orientation": [
                        -1.0,
                        -0.0,
                        -0.0,
                        -0.0,
                        -1.0,
                        -0.0,
                        0.0,
                        0.0,
                        1.0
                    ],
                    "selected": true,
                    "locked": false,
                    "visibility": true,
                    "positionStatus": "defined"
                },
                {
                    "id": "14",
                    "label": "Verse561_T3_ALL_S-22Verse561_T3_ALL_S-24",
                    "description": "",
                    "associatedNodeID": "",
                    "position": [
                        -9.0142822265625,
                        -110.89974212646484,
                        554.55615234375
                    ],
                    "orientation": [
                        -1.0,
                        -0.0,
                        -0.0,
                        -0.0,
                        -1.0,
                        -0.0,
                        0.0,
                        0.0,
                        1.0
                    ],
                    "selected": true,
                    "locked": false,
                    "visibility": true,
                    "positionStatus": "defined"
                },
                {
                    "id": "15",
                    "label": "Verse561_T3_ALL_S-25",
                    "description": "",
                    "associatedNodeID": "",
                    "position": [
                        -10.670537948608398,
                        -108.38355255126953,
                        555.1740112304688
                    ],
                    "orientation": [
                        -1.0,
                        -0.0,
                        -0.0,
                        -0.0,
                        -1.0,
                        -0.0,
                        0.0,
                        0.0,
                        1.0
                    ],
                    "selected": true,
                    "locked": false,
                    "visibility": true,
                    "positionStatus": "defined"
                }
            ],
            "measurements": [
                {
                    "name": "length",
                    "enabled": false,
                    "units": "mm",
                    "printFormat": "%-#4.4g%s"
                },
                {
                    "name": "curvature mean",
                    "enabled": false,
                    "printFormat": "%5.3f %s"
                },
                {
                    "name": "curvature max",
                    "enabled": false,
                    "printFormat": "%5.3f %s"
                },
                {
                    "name": "torsion mean",
                    "enabled": false,
                    "printFormat": "%5.3f %s"
                },
                {
                    "name": "torsion max",
                    "enabled": false,
                    "printFormat": "%5.3f %s"
                }
            ],
            "display": {
                "visibility": true,
                "opacity": 1.0,
                "color": [
                    0.0,
                    1.0,
                    0.0
                ],
                "selectedColor": [
                    0.0,
                    1.0,
                    0.0
                ],
                "activeColor": [
                    0.4,
                    1.0,
                    0.0
                ],
                "propertiesLabelVisibility": true,
                "pointLabelsVisibility": false,
                "textScale": 0.0,
                "glyphType": "Sphere3D",
                "glyphScale": 3.0,
                "glyphSize": 5.0,
                "useGlyphScale": true,
                "sliceProjection": false,
                "sliceProjectionUseFiducialColor": true,
                "sliceProjectionOutlinedBehindSlicePlane": false,
                "sliceProjectionColor": [
                    1.0,
                    1.0,
                    1.0
                ],
                "sliceProjectionOpacity": 0.6,
                "lineThickness": 0.2,
                "lineColorFadingStart": 1.0,
                "lineColorFadingEnd": 10.0,
                "lineColorFadingSaturation": 1.0,
                "lineColorFadingHueOffset": 0.0,
                "handlesInteractive": false,
                "translationHandleVisibility": true,
                "rotationHandleVisibility": true,
                "scaleHandleVisibility": true,
                "interactionHandleScale": 3.0,
                "snapMode": "toVisibleSurface"
            }
        }
    ]
}